frail/__init__.py
frail/ast.py
frail/debug_printer.py
frail/examples.py
frail/smt_printer.py
frail/smt_utils.py
frail/verilog_printer.py
frail-0.0.3.dist-info/LICENSE
frail-0.0.3.dist-info/METADATA
frail-0.0.3.dist-info/WHEEL
frail-0.0.3.dist-info/top_level.txt
frail-0.0.3.dist-info/RECORD
