Metadata-Version: 2.1
Name: frail
Version: 0.0.3
Summary: Create and prove equivalence of affine indexing hardware using recurrence relations encoded in scans
Home-page: https://github.com/David-Durst/frail
Maintainer: David Durst
Maintainer-email: davidbdurst@gmail.com
License: MIT
Platform: UNKNOWN
Requires-Python: >=3.8
Requires-Dist: pysmt
Requires-Dist: fault
